kube_hunter_dns_spoof.py
kube_hunter_dns_spoof-0.0.0.dist-info/LICENSE
kube_hunter_dns_spoof-0.0.0.dist-info/METADATA
kube_hunter_dns_spoof-0.0.0.dist-info/WHEEL
kube_hunter_dns_spoof-0.0.0.dist-info/entry_points.txt
kube_hunter_dns_spoof-0.0.0.dist-info/top_level.txt
kube_hunter_dns_spoof-0.0.0.dist-info/RECORD
