Metadata-Version: 2.1
Name: kube-hunter-dns-spoof
Version: 0.0.0
Summary: kube-hunter plugin for dns spoofing
Home-page: https://github.com/aquasecurity/kube-hunter-plugins
Author: Aqua Security
Author-email: support@aquasec.com
License: UNKNOWN
Keywords: aquasec,hunter,kubernetes,k8s,security,dns,spoofing
Platform: UNKNOWN
Classifier: Development Status :: 4 - Beta
Classifier: Environment :: Console
Classifier: License :: OSI Approved :: GNU General Public License v2 (GPLv2)
Classifier: Natural Language :: English
Classifier: Operating System :: OS Independent
Classifier: Programming Language :: Python :: 3.6
Classifier: Programming Language :: Python :: 3.7
Classifier: Programming Language :: Python :: 3.8
Classifier: Programming Language :: Python :: 3.9
Classifier: Programming Language :: Python :: 3 :: Only
Classifier: Topic :: Security
Requires-Dist: kube-hunter
Requires-Dist: kube-hunter-arp-spoof
Requires-Dist: scapy (>=2.4.3)
